includemacro/__init__.py
includemacro/macros.py
TracIncludeMacro-3.2.0.dist-info/COPYING
TracIncludeMacro-3.2.0.dist-info/METADATA
TracIncludeMacro-3.2.0.dist-info/WHEEL
TracIncludeMacro-3.2.0.dist-info/entry_points.txt
TracIncludeMacro-3.2.0.dist-info/top_level.txt
TracIncludeMacro-3.2.0.dist-info/RECORD
