Metadata-Version: 2.1
Name: TracIncludeMacro
Version: 3.2.0
Summary: Include the contents of external URLs and other Trac objects in a wiki page.
Home-page: http://trac-hacks.org/wiki/IncludeMacro
Author: Noah Kantrowitz
Author-email: noah@coderanger.net
Maintainer: Ryan J Ollos
Maintainer-email: ryan.j.ollos@gmail.com
License: 3-Clause BSD
Keywords: trac 1.0+ plugin wiki include macro
Platform: UNKNOWN
Classifier: Framework :: Trac
Requires-Dist: Trac
